<mxfile host="app.diagrams.net">
  <diagram name="性能对比图" id="performance_comparison">
    <mxGraphModel dx="1426" dy="881" grid="1" gridSize="10" guides="1" tooltips="1" connect="1" arrows="1" fold="1" page="1" pageScale="1" pageWidth="827" pageHeight="1169" math="0" shadow="0">
      <root>
        <mxCell id="0"/>
        <mxCell id="1" parent="0"/>
        
        <!-- 主标题 -->
        <mxCell id="title" value="CBDRI与基线模型性能对比" style="text;html=1;strokeColor=none;fillColor=none;align=center;verticalAlign=middle;whiteSpace=wrap;rounded=0;fontSize=20;fontStyle=1" vertex="1" parent="1">
          <mxGeometry x="300" y="20" width="250" height="30" as="geometry"/>
        </mxCell>
        
        <!-- 三个子图区域 -->
        
        <!-- MSE 子图 -->
        <mxCell id="mse_frame" value="" style="shape=rectangle;whiteSpace=wrap;html=1;rounded=1;fillColor=#f5f5f5;strokeColor=#cccccc;" vertex="1" parent="1">
          <mxGeometry x="50" y="70" width="220" height="180" as="geometry"/>
        </mxCell>
        
        <mxCell id="mse_title" value="预测误差 (MSE)" style="text;html=1;strokeColor=none;fillColor=none;align=center;verticalAlign=middle;whiteSpace=wrap;rounded=0;fontSize=14;fontStyle=1" vertex="1" parent="1">
          <mxGeometry x="50" y="75" width="220" height="20" as="geometry"/>
        </mxCell>
        
        <!-- MSE 柱状图 -->
        <mxCell id="mse_checklist" value="0.158" style="shape=cylinder3;whiteSpace=wrap;html=1;boundedLbl=1;backgroundOutline=1;size=15;fillColor=#4A90E2;strokeColor=#2D6DB5;fontSize=12;" vertex="1" parent="1">
          <mxGeometry x="80" y="135" width="40" height="105" as="geometry"/>
        </mxCell>
        
        <mxCell id="mse_dpi" value="0.165" style="shape=cylinder3;whiteSpace=wrap;html=1;boundedLbl=1;backgroundOutline=1;size=15;fillColor=#50E3C2;strokeColor=#2BB197;fontSize=12;" vertex="1" parent="1">
          <mxGeometry x="130" y="130" width="40" height="110" as="geometry"/>
        </mxCell>
        
        <mxCell id="mse_hmm" value="0.500" style="shape=cylinder3;whiteSpace=wrap;html=1;boundedLbl=1;backgroundOutline=1;size=15;fillColor=#F5A623;strokeColor=#D4890F;fontSize=12;" vertex="1" parent="1">
          <mxGeometry x="180" y="70" width="40" height="170" as="geometry"/>
        </mxCell>
        
        <mxCell id="mse_cbdri" value="0.090" style="shape=cylinder3;whiteSpace=wrap;html=1;boundedLbl=1;backgroundOutline=1;size=15;fillColor=#BD10E0;strokeColor=#8A0BA6;fontSize=12;fontStyle=1" vertex="1" parent="1">
          <mxGeometry x="80" y="170" width="40" height="70" as="geometry"/>
        </mxCell>
        
        <!-- MSE 模型标签 -->
        <mxCell id="mse_label1" value="清单法" style="text;html=1;strokeColor=none;fillColor=none;align=center;verticalAlign=middle;whiteSpace=wrap;rounded=0;fontSize=10;" vertex="1" parent="1">
          <mxGeometry x="80" y="245" width="40" height="15" as="geometry"/>
        </mxCell>
        
        <mxCell id="mse_label2" value="DPI" style="text;html=1;strokeColor=none;fillColor=none;align=center;verticalAlign=middle;whiteSpace=wrap;rounded=0;fontSize=10;" vertex="1" parent="1">
          <mxGeometry x="130" y="245" width="40" height="15" as="geometry"/>
        </mxCell>
        
        <mxCell id="mse_label3" value="HMM" style="text;html=1;strokeColor=none;fillColor=none;align=center;verticalAlign=middle;whiteSpace=wrap;rounded=0;fontSize=10;" vertex="1" parent="1">
          <mxGeometry x="180" y="245" width="40" height="15" as="geometry"/>
        </mxCell>
        
        <mxCell id="mse_label4" value="CBDRI" style="text;html=1;strokeColor=none;fillColor=none;align=center;verticalAlign=middle;whiteSpace=wrap;rounded=0;fontSize=10;fontStyle=1" vertex="1" parent="1">
          <mxGeometry x="80" y="265" width="40" height="15" as="geometry"/>
        </mxCell>
        
        <!-- FNR 子图 -->
        <mxCell id="fnr_frame" value="" style="shape=rectangle;whiteSpace=wrap;html=1;rounded=1;fillColor=#f5f5f5;strokeColor=#cccccc;" vertex="1" parent="1">
          <mxGeometry x="300" y="70" width="220" height="180" as="geometry"/>
        </mxCell>
        
        <mxCell id="fnr_title" value="假阴性率 (%)" style="text;html=1;strokeColor=none;fillColor=none;align=center;verticalAlign=middle;whiteSpace=wrap;rounded=0;fontSize=14;fontStyle=1" vertex="1" parent="1">
          <mxGeometry x="300" y="75" width="220" height="20" as="geometry"/>
        </mxCell>
        
        <!-- FNR 柱状图 -->
        <mxCell id="fnr_checklist" value="23.7" style="shape=cylinder3;whiteSpace=wrap;html=1;boundedLbl=1;backgroundOutline=1;size=15;fillColor=#4A90E2;strokeColor=#2D6DB5;fontSize=12;" vertex="1" parent="1">
          <mxGeometry x="330" y="100" width="40" height="140" as="geometry"/>
        </mxCell>
        
        <mxCell id="fnr_dpi" value="8.2" style="shape=cylinder3;whiteSpace=wrap;html=1;boundedLbl=1;backgroundOutline=1;size=15;fillColor=#50E3C2;strokeColor=#2BB197;fontSize=12;" vertex="1" parent="1">
          <mxGeometry x="380" y="160" width="40" height="80" as="geometry"/>
        </mxCell>
        
        <mxCell id="fnr_hmm" value="49.7" style="shape=cylinder3;whiteSpace=wrap;html=1;boundedLbl=1;backgroundOutline=1;size=15;fillColor=#F5A623;strokeColor=#D4890F;fontSize=12;" vertex="1" parent="1">
          <mxGeometry x="430" y="70" width="40" height="170" as="geometry"/>
        </mxCell>
        
        <mxCell id="fnr_cbdri" value="6.5" style="shape=cylinder3;whiteSpace=wrap;html=1;boundedLbl=1;backgroundOutline=1;size=15;fillColor=#BD10E0;strokeColor=#8A0BA6;fontSize=12;fontStyle=1" vertex="1" parent="1">
          <mxGeometry x="380" y="170" width="40" height="70" as="geometry"/>
        </mxCell>
        
        <!-- FNR 模型标签 -->
        <mxCell id="fnr_label1" value="清单法" style="text;html=1;strokeColor=none;fillColor=none;align=center;verticalAlign=middle;whiteSpace=wrap;rounded=0;fontSize=10;" vertex="1" parent="1">
          <mxGeometry x="330" y="245" width="40" height="15" as="geometry"/>
        </mxCell>
        
        <mxCell id="fnr_label2" value="DPI" style="text;html=1;strokeColor=none;fillColor=none;align=center;verticalAlign=middle;whiteSpace=wrap;rounded=0;fontSize=10;" vertex="1" parent="1">
          <mxGeometry x="380" y="245" width="40" height="15" as="geometry"/>
        </mxCell>
        
        <mxCell id="fnr_label3" value="HMM" style="text;html=1;strokeColor=none;fillColor=none;align=center;verticalAlign=middle;whiteSpace=wrap;rounded=0;fontSize=10;" vertex="1" parent="1">
          <mxGeometry x="430" y="245" width="40" height="15" as="geometry"/>
        </mxCell>
        
        <mxCell id="fnr_label4" value="CBDRI" style="text;html=1;strokeColor=none;fillColor=none;align=center;verticalAlign=middle;whiteSpace=wrap;rounded=0;fontSize=10;fontStyle=1" vertex="1" parent="1">
          <mxGeometry x="380" y="265" width="40" height="15" as="geometry"/>
        </mxCell>
        
        <!-- 成本子图 -->
        <mxCell id="cost_frame" value="" style="shape=rectangle;whiteSpace=wrap;html=1;rounded=1;fillColor=#f5f5f5;strokeColor=#cccccc;" vertex="1" parent="1">
          <mxGeometry x="550" y="70" width="220" height="180" as="geometry"/>
        </mxCell>
        
        <mxCell id="cost_title" value="合规成本 (相对)" style="text;html=1;strokeColor=none;fillColor=none;align=center;verticalAlign=middle;whiteSpace=wrap;rounded=0;fontSize=14;fontStyle=1" vertex="1" parent="1">
          <mxGeometry x="550" y="75" width="220" height="20" as="geometry"/>
        </mxCell>
        
        <!-- 成本柱状图 -->
        <mxCell id="cost_checklist" value="1.00" style="shape=cylinder3;whiteSpace=wrap;html=1;boundedLbl=1;backgroundOutline=1;size=15;fillColor=#4A90E2;strokeColor=#2D6DB5;fontSize=12;" vertex="1" parent="1">
          <mxGeometry x="580" y="80" width="40" height="160" as="geometry"/>
        </mxCell>
        
        <mxCell id="cost_dpi" value="1.11" style="shape=cylinder3;whiteSpace=wrap;html=1;boundedLbl=1;backgroundOutline=1;size=15;fillColor=#50E3C2;strokeColor=#2BB197;fontSize=12;" vertex="1" parent="1">
          <mxGeometry x="630" y="70" width="40" height="170" as="geometry"/>
        </mxCell>
        
        <mxCell id="cost_hmm" value="0.98" style="shape=cylinder3;whiteSpace=wrap;html=1;boundedLbl=1;backgroundOutline=1;size=15;fillColor=#F5A623;strokeColor=#D4890F;fontSize=12;" vertex="1" parent="1">
          <mxGeometry x="680" y="82" width="40" height="158" as="geometry"/>
        </mxCell>
        
        <mxCell id="cost_cbdri" value="0.28" style="shape=cylinder3;whiteSpace=wrap;html=1;boundedLbl=1;backgroundOutline=1;size=15;fillColor=#BD10E0;strokeColor=#8A0BA6;fontSize=12;fontStyle=1" vertex="1" parent="1">
          <mxGeometry x="630" y="194" width="40" height="46" as="geometry"/>
        </mxCell>
        
        <!-- 成本模型标签 -->
        <mxCell id="cost_label1" value="清单法" style="text;html=1;strokeColor=none;fillColor=none;align=center;verticalAlign=middle;whiteSpace=wrap;rounded=0;fontSize=10;" vertex="1" parent="1">
          <mxGeometry x="580" y="245" width="40" height="15" as="geometry"/>
        </mxCell>
        
        <mxCell id="cost_label2" value="DPI" style="text;html=1;strokeColor=none;fillColor=none;align=center;verticalAlign=middle;whiteSpace=wrap;rounded=0;fontSize=10;" vertex="1" parent="1">
          <mxGeometry x="630" y="245" width="40" height="15" as="geometry"/>
        </mxCell>
        
        <mxCell id="cost_label3" value="HMM" style="text;html=1;strokeColor=none;fillColor=none;align=center;verticalAlign=middle;whiteSpace=wrap;rounded=0;fontSize=10;" vertex="1" parent="1">
          <mxGeometry x="680" y="245" width="40" height="15" as="geometry"/>
        </mxCell>
        
        <mxCell id="cost_label4" value="CBDRI" style="text;html=1;strokeColor=none;fillColor=none;align=center;verticalAlign=middle;whiteSpace=wrap;rounded=0;fontSize=10;fontStyle=1" vertex="1" parent="1">
          <mxGeometry x="630" y="265" width="40" height="15" as="geometry"/>
        </mxCell>
        
        <!-- 图例 -->
        <mxCell id="legend_frame" value="" style="shape=rectangle;whiteSpace=wrap;html=1;rounded=1;fillColor=#f8f8f8;strokeColor=#dddddd;" vertex="1" parent="1">
          <mxGeometry x="300" y="280" width="220" height="80" as="geometry"/>
        </mxCell>
        
        <mxCell id="legend_title" value="模型图例" style="text;html=1;strokeColor=none;fillColor=none;align=center;verticalAlign=middle;whiteSpace=wrap;rounded=0;fontSize=12;fontStyle=1" vertex="1" parent="1">
          <mxGeometry x="300" y="285" width="220" height="20" as="geometry"/>
        </mxCell>
        
        <!-- 图例项目 -->
        <mxCell id="legend_checklist" value="清单法" style="text;html=1;strokeColor=none;fillColor=none;align=left;verticalAlign=middle;whiteSpace=wrap;rounded=0;fontSize=11;" vertex="1" parent="1">
          <mxGeometry x="350" y="310" width="50" height="20" as="geometry"/>
        </mxCell>
        
        <mxCell id="legend_checklist_color" value="" style="shape=cylinder3;whiteSpace=wrap;html=1;boundedLbl=1;backgroundOutline=1;size=8;fillColor=#4A90E2;strokeColor=#2D6DB5;" vertex="1" parent="1">
          <mxGeometry x="320" y="310" width="20" height="20" as="geometry"/>
        </mxCell>
        
        <mxCell id="legend_dpi" value="DPI+阈值法" style="text;html=1;strokeColor=none;fillColor=none;align=left;verticalAlign=middle;whiteSpace=wrap;rounded=0;fontSize=11;" vertex="1" parent="1">
          <mxGeometry x="470" y="310" width="70" height="20" as="geometry"/>
        </mxCell>
        
        <mxCell id="legend_dpi_color" value="" style="shape=cylinder3;whiteSpace=wrap;html=1;boundedLbl=1;backgroundOutline=1;size=8;fillColor=#50E3C2;strokeColor=#2BB197;" vertex="1" parent="1">
          <mxGeometry x="440" y="310" width="20" height="20" as="geometry"/>
        </mxCell>
        
        <mxCell id="legend_hmm" value="静态HMM" style="text;html=1;strokeColor=none;fillColor=none;align=left;verticalAlign=middle;whiteSpace=wrap;rounded=0;fontSize=11;" vertex="1" parent="1">
          <mxGeometry x="350" y="335" width="60" height="20" as="geometry"/>
        </mxCell>
        
        <mxCell id="legend_hmm_color" value="" style="shape=cylinder3;whiteSpace=wrap;html=1;boundedLbl=1;backgroundOutline=1;size=8;fillColor=#F5A623;strokeColor=#D4890F;" vertex="1" parent="1">
          <mxGeometry x="320" y="335" width="20" height="20" as="geometry"/>
        </mxCell>
        
        <mxCell id="legend_cbdri" value="CBDRI (本文)" style="text;html=1;strokeColor=none;fillColor=none;align=left;verticalAlign=middle;whiteSpace=wrap;rounded=0;fontSize=11;fontStyle=1" vertex="1" parent="1">
          <mxGeometry x="470" y="335" width="80" height="20" as="geometry"/>
        </mxCell>
        
        <mxCell id="legend_cbdri_color" value="" style="shape=cylinder3;whiteSpace=wrap;html=1;boundedLbl=1;backgroundOutline=1;size=8;fillColor=#BD10E0;strokeColor=#8A0BA6;" vertex="1" parent="1">
          <mxGeometry x="440" y="335" width="20" height="20" as="geometry"/>
        </mxCell>
        
        <!-- 性能提升标注 -->
        <mxCell id="improvement_note" value="✓ CBDRI在三个指标上均表现最优：MSE降低43.0%，FNR降低72.6%，合规成本降低72.0%" style="text;html=1;strokeColor=none;fillColor=none;align=center;verticalAlign=middle;whiteSpace=wrap;rounded=0;fontSize=12;fontStyle=2" vertex="1" parent="1">
          <mxGeometry x="200" y="380" width="450" height="30" as="geometry"/>
        </mxCell>
        
      </root>
    </mxGraphModel>
  </diagram>
</mxfile>
